edsger/.gitignore
edsger/__init__.py
edsger/_version.py
edsger/bellman_ford.c
edsger/bellman_ford.cpython-312-x86_64-linux-musl.so
edsger/bellman_ford.pyi
edsger/bellman_ford.pyx
edsger/bfs.c
edsger/bfs.cpython-312-x86_64-linux-musl.so
edsger/bfs.pyi
edsger/bfs.pyx
edsger/commons.c
edsger/commons.cpython-312-x86_64-linux-musl.so
edsger/commons.pxd
edsger/commons.pyi
edsger/commons.pyx
edsger/dijkstra.c
edsger/dijkstra.cpython-312-x86_64-linux-musl.so
edsger/dijkstra.pyi
edsger/dijkstra.pyx
edsger/graph_importer.py
edsger/networks.py
edsger/path.py
edsger/path_tracking.c
edsger/path_tracking.cpython-312-x86_64-linux-musl.so
edsger/path_tracking.pyi
edsger/path_tracking.pyx
edsger/pq_4ary_dec_0b.c
edsger/pq_4ary_dec_0b.cpython-312-x86_64-linux-musl.so
edsger/pq_4ary_dec_0b.pxd
edsger/pq_4ary_dec_0b.pyx
edsger/prefetch_compat.h
edsger/spiess_florian.c
edsger/spiess_florian.cpython-312-x86_64-linux-musl.so
edsger/spiess_florian.pyi
edsger/spiess_florian.pyx
edsger/star.c
edsger/star.cpython-312-x86_64-linux-musl.so
edsger/star.pyi
edsger/star.pyx
edsger/utils.py
edsger-0.1.7.dist-info/METADATA
edsger-0.1.7.dist-info/WHEEL
edsger-0.1.7.dist-info/top_level.txt
edsger-0.1.7.dist-info/RECORD
edsger-0.1.7.dist-info/licenses/AUTHORS.rst
edsger-0.1.7.dist-info/licenses/LICENSE
