Metadata-Version: 2.4
Name: edsger
Version: 0.1.7
Summary: Graph algorithms in Cython.
Author-email: François Pacull <francois.pacull@architecture-performance.fr>
Maintainer-email: François Pacull <francois.pacull@architecture-performance.fr>
License: MIT License
Project-URL: Repository, https://github.com/aetperf/Edsger
Project-URL: Documentation, https://edsger.readthedocs.io
Keywords: python,graph,shortest path,Dijkstra
Platform: any
Classifier: Development Status :: 4 - Beta
Classifier: Programming Language :: Python :: 3
Classifier: Programming Language :: Python :: 3.10
Classifier: Programming Language :: Python :: 3.11
Classifier: Programming Language :: Python :: 3.12
Classifier: Programming Language :: Python :: 3.13
Classifier: Programming Language :: Python :: 3.14
Classifier: License :: OSI Approved :: MIT License
Classifier: Operating System :: OS Independent
Classifier: Topic :: Scientific/Engineering
Requires-Python: >=3.10
License-File: LICENSE
License-File: AUTHORS.rst
Requires-Dist: setuptools
Requires-Dist: setuptools_scm
Requires-Dist: numpy>=1.26
Requires-Dist: Cython>=3
Requires-Dist: pandas
Provides-Extra: dev
Requires-Dist: black; extra == "dev"
Provides-Extra: test
Requires-Dist: pytest; extra == "test"
Requires-Dist: scipy<1.11; extra == "test"
Provides-Extra: doc
Requires-Dist: sphinx; extra == "doc"
Requires-Dist: sphinx_design; extra == "doc"
Requires-Dist: sphinx_rtd_theme; extra == "doc"
Dynamic: license-file
